rlite/__init__.py
rlite/__version__.py
rlite/inference/__init__.py
rlite/inference/engine.py
rlite/inference/utils.py
rlite/inference/vllm/__init__.py
rlite/inference/vllm/executor.py
rlite/inference/vllm/worker.py
rlite/interface/__init__.py
rlite/interface/base_engine.py
rlite/interface/base_executor.py
rlite/interface/base_worker.py
rlite/interface/inference/__init__.py
rlite/interface/inference/inference_executor.py
rlite/interface/inference/inference_worker.py
rlite/interface/train/__init__.py
rlite/interface/train/train_executor.py
rlite/interface/train/train_worker.py
rlite/nn/__init__.py
rlite/nn/fsdp.py
rlite/nn/fsdp2.py
rlite/nn/inference_module.py
rlite/nn/train_module.py
rlite/resman/__init__.py
rlite/resman/resource_bundle.py
rlite/resman/resource_consumer.py
rlite/resman/resource_manager.py
rlite/third_party/__init__.py
rlite/third_party/transformers/__init__.py
rlite/third_party/transformers/monkey_patch.py
rlite/third_party/vllm/__init__.py
rlite/third_party/vllm/vllm_0_8_34.py
rlite/third_party/vllm/vllm_0_8_5.py
rlite/train/__init__.py
rlite/train/engine.py
rlite/train/fsdp/__init__.py
rlite/train/fsdp/executor.py
rlite/train/fsdp/worker.py
rlite/train/fsdp2/__init__.py
rlite/train/fsdp2/executor.py
rlite/train/fsdp2/worker.py
rlite/train/utils/__init__.py
rlite/train/utils/fsdp.py
rlite/train/utils/handle_parallel.py
rlite/utils/__init__.py
rlite/utils/async_context.py
rlite/utils/checkpoint.py
rlite/utils/distributed.py
rlite/utils/misc.py
rlite/utils/need_parallel.py
rlite/utils/registry.py
rlite/utils/tensorboard.py
pyrlite-0.1.2.dist-info/METADATA
pyrlite-0.1.2.dist-info/WHEEL
pyrlite-0.1.2.dist-info/RECORD
