Metadata-Version: 2.4
Name: pyrlite
Version: 0.1.2
Summary: A lightweight reinforcement learning framework that integrates seamlessly into your codebase, empowering developers to focus on algorithms with minimal intrusion.
Author-email: Han Zhang <zh950713@gmail.com>, Jingcheng Hu <hujc22@mails.tsinghua.edu.cn>, Zane Li <zengarden2009@gmail.com>
License-Expression: MIT
Requires-Python: >=3.10
Requires-Dist: accelerate>=0.26.0
Requires-Dist: cloudpickle
Requires-Dist: debugpy>=1.8.0
Requires-Dist: loguru
Requires-Dist: numpy
Requires-Dist: pandas
Requires-Dist: pynvml
Requires-Dist: ray
Requires-Dist: safetensors
Requires-Dist: tensorboard
Requires-Dist: torch>=2.6.0
Requires-Dist: torchaudio>=2.6.0
Requires-Dist: torchvision>=0.21.0
Requires-Dist: tqdm
Requires-Dist: vllm>=0.8.3
Provides-Extra: dev
Requires-Dist: pytest-cov>=3.0; extra == 'dev'
Requires-Dist: pytest>=7.0; extra == 'dev'
